gridworld_continuous/__init__.py
gridworld_continuous/base.py
gridworld_continuous/env.py
gridworld_continuous/envs.py
gridworld_continuous/events.py
gridworld_continuous/patches.py
gridworld_continuous/strings.py
gridworld_continuous-0.0.1.dist-info/LICENSE
gridworld_continuous-0.0.1.dist-info/METADATA
gridworld_continuous-0.0.1.dist-info/WHEEL
gridworld_continuous-0.0.1.dist-info/top_level.txt
gridworld_continuous-0.0.1.dist-info/RECORD
