Metadata-Version: 2.1
Name: gridworld-continuous
Version: 0.0.1
Summary: A simple implementation of a continuous GridWorld
Home-page: https://github.com/jordan-wei-taylor/continuous-gridworld
Author: Jordan Taylor
Author-email: jt2006@bath.ac.uk
License: Copyright (c) 2022, Jordan Wei Taylor
Project-URL: Bug Tracker, https://github.com/jordan-wei-taylor/continuous-gridworld/issues
Classifier: Programming Language :: Python :: 3
Classifier: Operating System :: OS Independent
Requires-Python: >=3.8
License-File: LICENSE
Requires-Dist: matplotlib (>=3.5.2)
Requires-Dist: numpy (>=1.22.3)
